optispec/__init__.py
optispec/hamiltonian.py
optispec/models/base.py
optispec/models/mlj.py
optispec/models/stark.py
optispec/models/two_state.py
optispec/utils.py
optispec-0.1.1.dist-info/METADATA
optispec-0.1.1.dist-info/WHEEL
optispec-0.1.1.dist-info/RECORD
