Metadata-Version: 2.1
Name: optispec
Version: 0.1.1
Summary: Simulate optical spectra with quantum mechanical models.
Author: benkoppe
Author-email: koppe@arizona.edu
Requires-Python: >=3.10,<4.0
Classifier: Programming Language :: Python :: 3
Classifier: Programming Language :: Python :: 3.10
Classifier: Programming Language :: Python :: 3.11
Classifier: Programming Language :: Python :: 3.12
Requires-Dist: jax (>=0.4.31,<0.5.0)
Requires-Dist: jax-dataclasses (>=1.6.1,<2.0.0)
Requires-Dist: jaxtyping (>=0.2.33,<0.3.0)
Requires-Dist: matplotlib (>=3.9.2,<4.0.0)
Requires-Dist: numpy (>=2.0.1,<3.0.0)
